spmat/linalg.c
spmat/__init__.py
spmat/utils.py
spmat/dlmat.py
spmat/linalg.pyx
spmat/linalg.cpython-312-darwin.so
spmat-0.1.1.dist-info/RECORD
spmat-0.1.1.dist-info/WHEEL
spmat-0.1.1.dist-info/top_level.txt
spmat-0.1.1.dist-info/METADATA
spmat-0.1.1.dist-info/licenses/LICENSE
