Metadata-Version: 2.4
Name: spmat
Version: 0.1.1
Summary: spmat: A collection of tools for special matrices
Author-email: IHME Math Sciences <ihme.math.sciences@gmail.com>
License-Expression: BSD-2-Clause
Project-URL: Homepage, https://github.com/ihmeuw-msca/spmat
Project-URL: Repository, https://github.com/ihmeuw-msca/spmat
Project-URL: Documentation, https://github.com/ihmeuw-msca/spmat
Keywords: matrices,linear-algebra,sparse-matrices
Classifier: Intended Audience :: Science/Research
Classifier: Operating System :: OS Independent
Classifier: Programming Language :: Python :: 3
Classifier: Programming Language :: Python :: 3 :: Only
Classifier: Programming Language :: Python :: 3.10
Classifier: Programming Language :: Python :: 3.11
Classifier: Programming Language :: Python :: 3.12
Classifier: Programming Language :: Python :: 3.13
Classifier: Topic :: Scientific/Engineering :: Mathematics
Requires-Python: <3.14,>=3.10
License-File: LICENSE
Requires-Dist: numpy
Requires-Dist: scipy
Provides-Extra: dev
Requires-Dist: pytest; extra == "dev"
Dynamic: license-file
